QinghuiPmpJiangyiBiaozhunbanV182Fix1/README.md
QinghuiPmpJiangyiBiaozhunbanV182Fix1/__init__.py
QinghuiPmpJiangyiBiaozhunbanV182Fix1/__main__.py
QinghuiPmpJiangyiBiaozhunbanV182Fix1/file.pdf
QinghuiPmpJiangyiBiaozhunbanV182Fix1/index.html
qinghui_pmp_jiangyi_biaozhunban_v1_8_2_fix1-2025.3.25.1.dist-info/METADATA
qinghui_pmp_jiangyi_biaozhunban_v1_8_2_fix1-2025.3.25.1.dist-info/WHEEL
qinghui_pmp_jiangyi_biaozhunban_v1_8_2_fix1-2025.3.25.1.dist-info/entry_points.txt
qinghui_pmp_jiangyi_biaozhunban_v1_8_2_fix1-2025.3.25.1.dist-info/top_level.txt
qinghui_pmp_jiangyi_biaozhunban_v1_8_2_fix1-2025.3.25.1.dist-info/RECORD
